async_channel/__init__.pxd
async_channel/__init__.py
async_channel/constants.py
async_channel/consumer.cp38-win_amd64.pyd
async_channel/consumer.pxd
async_channel/consumer.py
async_channel/enums.py
async_channel/producer.cp38-win_amd64.pyd
async_channel/producer.pxd
async_channel/producer.py
async_channel/channels/__init__.pxd
async_channel/channels/__init__.py
async_channel/channels/channel.cp38-win_amd64.pyd
async_channel/channels/channel.pxd
async_channel/channels/channel.py
async_channel/channels/channel_instances.cp38-win_amd64.pyd
async_channel/channels/channel_instances.pxd
async_channel/channels/channel_instances.py
async_channel/util/__init__.pxd
async_channel/util/__init__.py
async_channel/util/channel_creator.cp38-win_amd64.pyd
async_channel/util/channel_creator.pxd
async_channel/util/channel_creator.py
async_channel/util/logging_util.py
async_channel-2.1.0.dist-info/LICENSE
async_channel-2.1.0.dist-info/METADATA
async_channel-2.1.0.dist-info/WHEEL
async_channel-2.1.0.dist-info/top_level.txt
async_channel-2.1.0.dist-info/RECORD
