Metadata-Version: 2.1
Name: async-channel
Version: 2.1.0
Summary: Python channel based communication library
Home-page: https://github.com/Drakkar-Software/Async-Channel
Author: Drakkar-Software
Author-email: drakkar-software@protonmail.com
License: LGPL-3.0
Platform: UNKNOWN
Classifier: Development Status :: 5 - Production/Stable
Classifier: Operating System :: OS Independent
Classifier: Operating System :: MacOS :: MacOS X
Classifier: Operating System :: Microsoft :: Windows
Classifier: Operating System :: POSIX
Classifier: Programming Language :: Python :: 3.8
Classifier: Programming Language :: Python :: 3.9
Classifier: Programming Language :: Cython
Classifier: Environment :: Console
Requires-Python: >=3.8
Requires-Dist: cython (==0.29.32)
